fifo_sync.v
module fifo_sync 
    #(  parameter FIFO_DEPTH = 8,
        parameter DATA_WIDTH = 32)
      ( 
        input clk,
        input cs,
        input rst_n,
        input wr_en,
        input rd_en,
        input [DATA_WIDTH-1:0] data_in,
        output reg [DATA_WIDTH-1:0] data_out,
        output empty,
        output full);
   localparam PTR_WIDTH = $clog2(FIFO_DEPTH);
   reg [DATA_WIDTH-1:0] fifo [0:FIFO_DEPTH-1];
   reg [PTR_WIDTH:0] write_pointer;
   reg [PTR_WIDTH:0] read_pointer;
   always @(posedge clk or negedge rst_n) 
   begin 
     if (!rst_n) 
        begin 
            write_pointer <= 0;
        end 
     else if (cs && wr_en && (!full || (rd_en && !empty)))
         begin 
            fifo[write_pointer[PTR_WIDTH-1:0]] <= data_in;
            write_pointer <= write_pointer + 1'b1;
         end
    end
    always @(posedge clk or negedge rst_n) 
    begin 
      if (!rst_n) 
         begin
            read_pointer <= 0;
            data_out <= {DATA_WIDTH{1'b0}}; 
         end 
      else if (cs && rd_en && !empty)
         begin 
            data_out <= fifo[read_pointer[PTR_WIDTH-1:0]];
            read_pointer <= read_pointer + 1'b1;
         end
   end
   assign empty = (read_pointer == write_pointer);
   assign full = (write_pointer == {~read_pointer[PTR_WIDTH], read_pointer[PTR_WIDTH-1:0]});
endmodule

fifo_sync_tb.v
`timescale 1ns/1ns
module fifo_sync_tb;
    parameter FIFO_DEPTH = 8, DATA_WIDTH = 32;
    reg clk, cs, rst_n, wr_en, rd_en;
    reg [DATA_WIDTH-1:0] data_in;
    reg [DATA_WIDTH-1:0] expected_queue [0:255];
    wire [DATA_WIDTH-1:0] data_out;
    wire empty, full;
    integer i, error_count = 0, wr_idx = 0, rd_idx = 0;
    fifo_sync #(.FIFO_DEPTH(FIFO_DEPTH), .DATA_WIDTH(DATA_WIDTH)) 
    dut (
        .clk(clk),
        .cs(cs),
        .rst_n(rst_n),
        .wr_en(wr_en),
        .rd_en(rd_en),
        .data_in(data_in),
        .data_out(data_out),
        .empty(empty),
        .full(full));
    always #5 clk = ~clk;
    task write_data(input [DATA_WIDTH-1:0] d_in);
    begin
        @(posedge clk);
        if (!full)
        begin
            cs = 1; wr_en = 1; rd_en = 0; data_in = d_in;
            expected_queue[wr_idx] = d_in;
            wr_idx = wr_idx + 1;
            $display("[%0t ns] WRITE: %0d | Full=%b Empty=%b", $time, d_in, full, empty);
            @(posedge clk);
            wr_en = 0;
        end else
            $display("[%0t ns] WRITE BLOCKED (FULL): %0d", $time, d_in);
    end
    endtask
    task read_data();
        reg [DATA_WIDTH-1:0] exp_val;
    begin
        @(posedge clk);
        if (!empty)
        begin
            cs = 1; rd_en = 1; wr_en = 0;
            exp_val = expected_queue[rd_idx];
            rd_idx = rd_idx + 1;
            @(posedge clk);
            rd_en = 0;
            #1;
            if (data_out === exp_val)
                $display("[%0t ns] READ OK: %0d | Full=%b Empty=%b", $time, data_out, full, empty);
            else
                begin
                $display("[%0t ns] ERROR: Exp %0d, Got %0d", $time, exp_val, data_out);
                error_count = error_count + 1;
                end
        end else
            $display("[%0t ns] READ BLOCKED (EMPTY)", $time);
    end
    endtask
    task write_and_read(input [DATA_WIDTH-1:0] d_in);
        reg [DATA_WIDTH-1:0] exp_val;
    begin
        @(posedge clk);
        cs = 1; wr_en = 1; rd_en = 1; data_in = d_in;
        if (!full || !empty)
        begin
            expected_queue[wr_idx] = d_in;
            wr_idx = wr_idx + 1;
        end
        if (!empty)
        begin
            exp_val = expected_queue[rd_idx];
            rd_idx = rd_idx + 1;
        end
        $display("[%0t ns] SIMULTANEOUS W/R: wr=%0d", $time, d_in);
        @(posedge clk);
        wr_en = 0; rd_en = 0;
        #1;
        if (!empty)
        begin
            if (data_out === exp_val)
                $display("[%0t ns] SIM-READ OK: %0d", $time, data_out);
            else
                begin
                $display("[%0t ns] ERROR Sim-Read: Exp %0d, Got %0d", $time, exp_val, data_out);
                error_count = error_count + 1;
                end
        end
    end
    endtask
    initial
     begin
        $dumpfile("fifo_tb.vcd");
        $dumpvars(0, fifo_sync_tb);
        clk = 0; cs = 0; rst_n = 0; wr_en = 0; rd_en = 0; data_in = 0;
        #20 rst_n = 1; #10;
        write_data(101); read_data();
        write_data(102); read_data();
        write_data(201); write_data(202); write_data(203);

        read_data();
        write_data(204); write_data(205); write_data(206);
        read_data(); read_data(); read_data();

        for (i = 1; i <= 9; i = i + 1) write_data(900 + i);
        while (!empty) read_data();

        for (i = 1; i <= 5; i = i + 1) write_data(300 + i);
        for (i = 1; i <= 5; i = i + 1) read_data();
        for (i = 6; i <= 10; i = i + 1) write_data(300 + i);
        while (!empty) read_data();

        write_data(401); write_data(402);
        write_and_read(403);
        while (!empty) read_data();
        #20;
        if (error_count == 0) $display("SUCCESS: ALL TESTS PASSED");
        else $display("FAILURE: %0d ERRORS FOUND", error_count);
        $finish;
     end
endmodule

fifo_tb.vcd
$date
	Sat Aug  8 22:20:01 2026
$end
$version
	Icarus Verilog
$end
$timescale
	1ns
$end
$scope module fifo_sync_tb $end
$var wire 1 ! full $end
$var wire 1 " empty $end
$var wire 32 # data_out [31:0] $end
$var parameter 32 $ DATA_WIDTH $end
$var parameter 32 % FIFO_DEPTH $end
$var reg 1 & clk $end
$var reg 1 ' cs $end
$var reg 32 ( data_in [31:0] $end
$var reg 1 ) rd_en $end
$var reg 1 * rst_n $end
$var reg 1 + wr_en $end
$var integer 32 , error_count [31:0] $end
$var integer 32 - i [31:0] $end
$var integer 32 . rd_idx [31:0] $end
$var integer 32 / wr_idx [31:0] $end
$scope module dut $end
$var wire 1 & clk $end
$var wire 1 ' cs $end
$var wire 32 0 data_in [31:0] $end
$var wire 1 ) rd_en $end
$var wire 1 * rst_n $end
$var wire 1 + wr_en $end
$var wire 1 ! full $end
$var wire 1 " empty $end
$var parameter 32 1 DATA_WIDTH $end
$var parameter 32 2 FIFO_DEPTH $end
$var parameter 32 3 PTR_WIDTH $end
$var reg 32 4 data_out [31:0] $end
$var reg 4 5 read_pointer [3:0] $end
$var reg 4 6 write_pointer [3:0] $end
$upscope $end
$scope task read_data $end
$var reg 32 7 exp_val [31:0] $end
$upscope $end
$scope task write_and_read $end
$var reg 32 8 d_in [31:0] $end
$var reg 32 9 exp_val [31:0] $end
$upscope $end
$scope task write_data $end
$var reg 32 : d_in [31:0] $end
$upscope $end
$upscope $end
$enddefinitions $end
$comment Show the parameter values. $end
$dumpall
b11 3
b1000 2
b100000 1
b1000 %
b100000 $
$end
#0
$dumpvars
bx :
bx 9
bx 8
bx 7
b0 6
b0 5
b0 4
b0 0
b0 /
b0 .
bx -
b0 ,
0+
0*
0)
b0 (
0'
0&
b0 #
1"
0!
$end
#5
1&
#10
0&
#15
1&
#20
0&
1*
#25
1&
#30
0&
b1100101 :
#35
0"
b1 6
b1 /
b1100101 (
b1100101 0
1+
1'
1&
#40
0&
#45
0+
1&
#50
0&
#55
1"
b1 5
b1100101 #
b1100101 4
b1 .
b1100101 7
1)
1&
#60
0&
#65
0)
1&
#66
b1100110 :
#70
0&
#75
0"
b10 6
b10 /
b1100110 (
b1100110 0
1+
1&
#80
0&
#85
0+
1&
#90
0&
#95
1"
b10 5
b1100110 #
b1100110 4
b10 .
b1100110 7
1)
1&
#100
0&
#105
0)
1&
#106
b11001001 :
#110
0&
#115
0"
b11 6
b11 /
b11001001 (
b11001001 0
1+
1&
#120
0&
#125
b11001010 :
0+
1&
#130
0&
#135
b100 6
b100 /
b11001010 (
b11001010 0
1+
1&
#140
0&
#145
b11001011 :
0+
1&
#150
0&
#155
b101 6
b101 /
b11001011 (
b11001011 0
1+
1&
#160
0&
#165
0+
1&
#170
0&
#175
b11 5
b11001001 #
b11001001 4
b11 .
b11001001 7
1)
1&
#180
0&
#185
0)
1&
#186
b11001100 :
#190
0&
#195
b110 6
b110 /
b11001100 (
b11001100 0
1+
1&
#200
0&
#205
b11001101 :
0+
1&
#210
0&
#215
b111 6
b111 /
b11001101 (
b11001101 0
1+
1&
#220
0&
#225
b11001110 :
0+
1&
#230
0&
#235
b1000 6
b1000 /
b11001110 (
b11001110 0
1+
1&
#240
0&
#245
0+
1&
#250
0&
#255
b100 5
b11001010 #
b11001010 4
b100 .
b11001010 7
1)
1&
#260
0&
#265
0)
1&
#270
0&
#275
b101 5
b11001011 #
b11001011 4
b101 .
b11001011 7
1)
1&
#280
0&
#285
0)
1&
#290
0&
#295
b110 5
b11001100 #
b11001100 4
b110 .
b11001100 7
1)
1&
#300
0&
#305
0)
1&
#306
b1110000101 :
b1 -
#310
0&
#315
b1001 6
b1001 /
b1110000101 (
b1110000101 0
1+
1&
#320
0&
#325
b1110000110 :
b10 -
0+
1&
#330
0&
#335
b1010 6
b1010 /
b1110000110 (
b1110000110 0
1+
1&
#340
0&
#345
b1110000111 :
b11 -
0+
1&
#350
0&
#355
b1011 6
b1011 /
b1110000111 (
b1110000111 0
1+
1&
#360
0&
#365
b1110001000 :
b100 -
0+
1&
#370
0&
#375
b1100 6
b1100 /
b1110001000 (
b1110001000 0
1+
1&
#380
0&
#385
b1110001001 :
b101 -
0+
1&
#390
0&
#395
b1101 6
b1101 /
b1110001001 (
b1110001001 0
1+
1&
#400
0&
#405
b1110001010 :
b110 -
0+
1&
#410
0&
#415
1!
b1110 6
b1110 /
b1110001010 (
b1110001010 0
1+
1&
#420
0&
#425
b1110001011 :
b111 -
0+
1&
#430
0&
#435
b1110001100 :
b1000 -
1&
#440
0&
#445
b1110001101 :
b1001 -
1&
#450
0&
#455
b1010 -
1&
#460
0&
#465
0!
b111 5
b11001101 #
b11001101 4
b111 .
b11001101 7
1)
1&
#470
0&
#475
0)
1&
#480
0&
#485
b1000 5
b11001110 #
b11001110 4
b1000 .
b11001110 7
1)
1&
#490
0&
#495
0)
1&
#500
0&
#505
b1001 5
b1110000101 #
b1110000101 4
b1001 .
b1110000101 7
1)
1&
#510
0&
#515
0)
1&
#520
0&
#525
b1010 5
b1110000110 #
b1110000110 4
b1010 .
b1110000110 7
1)
1&
#530
0&
#535
0)
1&
#540
0&
#545
b1011 5
b1110000111 #
b1110000111 4
b1011 .
b1110000111 7
1)
1&
#550
0&
#555
0)
1&
#560
0&
#565
b1100 5
b1110001000 #
b1110001000 4
b1100 .
b1110001000 7
1)
1&
#570
0&
#575
0)
1&
#580
0&
#585
b1101 5
b1110001001 #
b1110001001 4
b1101 .
b1110001001 7
1)
1&
#590
0&
#595
0)
1&
#600
0&
#605
1"
b1110 5
b1110001010 #
b1110001010 4
b1110 .
b1110001010 7
1)
1&
#610
0&
#615
0)
1&
#616
b100101101 :
b1 -
#620
0&
#625
0"
b1111 6
b1111 /
b100101101 (
b100101101 0
1+
1&
#630
0&
#635
b100101110 :
b10 -
0+
1&
#640
0&
#645
b0 6
b10000 /
b100101110 (
b100101110 0
1+
1&
#650
0&
#655
b100101111 :
b11 -
0+
1&
#660
0&
#665
b1 6
b10001 /
b100101111 (
b100101111 0
1+
1&
#670
0&
#675
b100110000 :
b100 -
0+
1&
#680
0&
#685
b10 6
b10010 /
b100110000 (
b100110000 0
1+
1&
#690
0&
#695
b100110001 :
b101 -
0+
1&
#700
0&
#705
b11 6
b10011 /
b100110001 (
b100110001 0
1+
1&
#710
0&
#715
b1 -
0+
1&
#720
0&
#725
b1111 5
b100101101 #
b100101101 4
b1111 .
b100101101 7
1)
1&
#730
0&
#735
0)
1&
#736
b10 -
#740
0&
#745
b0 5
b100101110 #
b100101110 4
b10000 .
b100101110 7
1)
1&
#750
0&
#755
0)
1&
#756
b11 -
#760
0&
#765
b1 5
b100101111 #
b100101111 4
b10001 .
b100101111 7
1)
1&
#770
0&
#775
0)
1&
#776
b100 -
#780
0&
#785
b10 5
b100110000 #
b100110000 4
b10010 .
b100110000 7
1)
1&
#790
0&
#795
0)
1&
#796
b101 -
#800
0&
#805
1"
b11 5
b100110001 #
b100110001 4
b10011 .
b100110001 7
1)
1&
#810
0&
#815
0)
1&
#816
b100110010 :
b110 -
#820
0&
#825
0"
b100 6
b10100 /
b100110010 (
b100110010 0
1+
1&
#830
0&
#835
b100110011 :
b111 -
0+
1&
#840
0&
#845
b101 6
b10101 /
b100110011 (
b100110011 0
1+
1&
#850
0&
#855
b100110100 :
b1000 -
0+
1&
#860
0&
#865
b110 6
b10110 /
b100110100 (
b100110100 0
1+
1&
#870
0&
#875
b100110101 :
b1001 -
0+
1&
#880
0&
#885
b111 6
b10111 /
b100110101 (
b100110101 0
1+
1&
#890
0&
#895
b100110110 :
b1010 -
0+
1&
#900
0&
#905
b1000 6
b11000 /
b100110110 (
b100110110 0
1+
1&
#910
0&
#915
b1011 -
0+
1&
#920
0&
#925
b100 5
b100110010 #
b100110010 4
b10100 .
b100110010 7
1)
1&
#930
0&
#935
0)
1&
#940
0&
#945
b101 5
b100110011 #
b100110011 4
b10101 .
b100110011 7
1)
1&
#950
0&
#955
0)
1&
#960
0&
#965
b110 5
b100110100 #
b100110100 4
b10110 .
b100110100 7
1)
1&
#970
0&
#975
0)
1&
#980
0&
#985
b111 5
b100110101 #
b100110101 4
b10111 .
b100110101 7
1)
1&
#990
0&
#995
0)
1&
#1000
0&
#1005
0!
1"
b1000 5
b100110110 #
b100110110 4
b11000 .
b100110110 7
1)
1&
#1010
0&
#1015
0)
1&
#1016
b110010001 :
#1020
0&
#1025
0"
b1001 6
b11001 /
b110010001 (
b110010001 0
1+
1&
#1030
0&
#1035
b110010010 :
0+
1&
#1040
0&
#1045
b1010 6
b11010 /
b110010010 (
b110010010 0
1+
1&
#1050
0&
#1055
b110010011 8
0+
1&
#1060
0&
#1065
b1001 5
b110010001 #
b110010001 4
b1011 6
b11001 .
b110010001 9
b11011 /
b110010011 (
b110010011 0
1)
1+
1&
#1070
0&
#1075
0)
0+
1&
#1080
0&
#1085
b1010 5
b110010010 #
b110010010 4
b11010 .
b110010010 7
1)
1&
#1090
0&
#1095
0)
1&
#1100
0&
#1105
1"
b1011 5
b110010011 #
b110010011 4
b11011 .
b110010011 7
1)
1&
#1110
0&
#1115
0)
1&
